{
    "flag": true,
    "msg": "LOAD_SUCCESS",
    "data": [{
        "serviceTypeId": "8c1f26f383864a18b04c3e5a1dc76e81",
        "serviceTypeName": "搬家服务",
        "children": [{
            "serviceTypeId": "8905d3dae5af4f7484109abd4bbedffe",
            "serviceTypeName": "远程搬家",
            "ischecked": true
        }],
        "ischecked": true
    }, {
        "serviceTypeId": "c951d95476694213a91e51b22b2237fe",
        "serviceTypeName": "家电维修",
        "children": [{
            "serviceTypeId": "6c3321eead444dd7a853dbe84d14ca69",
            "serviceTypeName": "电视机维修",
            "ischecked": false
        }, {
            "serviceTypeId": "ccb616f21fbd417ca291c1b7ef5afa18",
            "serviceTypeName": "电脑维护",
            "ischecked": false
        }, {
            "serviceTypeId": "404e2087b300456fbf88d83aaeb74530",
            "serviceTypeName": "维修洗衣机维修",
            "ischecked": true
        }, {
            "serviceTypeId": "726a4230d07f4f7181e3919ea1fc28eb",
            "serviceTypeName": "冰箱维修",
            "ischecked": false
        }, {
            "serviceTypeId": "0e7cbbda351c4b2cadee00e6293e39b7",
            "serviceTypeName": "空调维修",
            "ischecked": false
        }, {
            "serviceTypeId": "706398a8e8ff41e4a86f21ee8acce10b",
            "serviceTypeName": "电脑维修",
            "ischecked": false
        }, {
            "serviceTypeId": "c29cf26467c24dacb2298920ac924786",
            "serviceTypeName": "抽油烟机专业维修",
            "ischecked": false
        }, {
            "serviceTypeId": "3f999b1639a14a869470f629d3cef63f",
            "serviceTypeName": "电吹风维修",
            "ischecked": false
        }, {
            "serviceTypeId": "3ccf97d4ca6b44c6a066f6a7fa3f0ca2",
            "serviceTypeName": "机顶盒维修",
            "ischecked": false
        }, {
            "serviceTypeId": "5b70d05cb13d46d9a8907ae86e36354f",
            "serviceTypeName": "电风扇维修",
            "ischecked": false
        }, {
            "serviceTypeId": "260dd9294a904dd4a13d37185bc485e6",
            "serviceTypeName": "烘鞋器维修",
            "ischecked": false
        }],
        "ischecked": true
    }, {
        "serviceTypeId": "54e739bc84244d6ba60c7e326b7a2a43",
        "serviceTypeName": "月嫂",
        "children": [{
            "serviceTypeId": "8e4d085e083d45d59954d43e6004cf89",
            "serviceTypeName": "高级月嫂",
            "ischecked": false
        }, {
            "serviceTypeId": "ff5c02f7f0fc4efd9cec21e43c2e5803",
            "serviceTypeName": "中级月嫂",
            "ischecked": false
        }, {
            "serviceTypeId": "1d6b8a927fff4c538e0e23dbe93bf817",
            "serviceTypeName": "初级月嫂",
            "ischecked": false
        }, {
            "serviceTypeId": "4740dcc4d8f54f988b92c7ad8ba60d42",
            "serviceTypeName": "超级月嫂",
            "ischecked": false
        }, {
            "serviceTypeId": "8574e77f333b4db5be1f6302edfdcfab",
            "serviceTypeName": "无敌月嫂",
            "ischecked": false
        }, {
            "serviceTypeId": "0a3afd0fb161464aa2b23cd00a9fdc76",
            "serviceTypeName": "住家月嫂",
            "ischecked": false
        }],
        "ischecked": false
    }, {
        "serviceTypeId": "70a636938a5248b4914c83f5d26e9fb2",
        "serviceTypeName": "育婴师",
        "children": [{
            "serviceTypeId": "bb56649632ac4c96a1e58f9c75c77442",
            "serviceTypeName": "高级育婴师",
            "ischecked": false
        }, {
            "serviceTypeId": "81fe607e4fa447359cd0960be638bb59",
            "serviceTypeName": "中级育婴师",
            "ischecked": false
        }, {
            "serviceTypeId": "8ad6aa60e68746639cd09a886d532d87",
            "serviceTypeName": "初级育婴师",
            "ischecked": false
        }, {
            "serviceTypeId": "b1e3d72259464f98b6a1b87aa46af6b7",
            "serviceTypeName": "超级育婴师",
            "ischecked": false
        }, {
            "serviceTypeId": "bf765dfd578e4c218dcf5ae3e4af4b26",
            "serviceTypeName": "无敌育婴师",
            "ischecked": false
        }],
        "ischecked": false
    }, {
        "serviceTypeId": "348ec37091ca4e4fb685c88a788ecce4",
        "serviceTypeName": "钟点工",
        "children": [{
            "serviceTypeId": "1415436f43c245b3a5bb69242205bbea",
            "serviceTypeName": "翻译钟点工",
            "ischecked": false
        }, {
            "serviceTypeId": "7d955c80d27c4261a8006c5a6c986689",
            "serviceTypeName": "餐饮服务钟点工",
            "ischecked": false
        }, {
            "serviceTypeId": "ab327a394ac34797aabee5a8bec4a7a4",
            "serviceTypeName": "家教钟点工",
            "ischecked": false
        }, {
            "serviceTypeId": "943023b11e94421ab25a117f6d500b94",
            "serviceTypeName": "清理马桶钟点工",
            "ischecked": false
        }],
        "ischecked": false
    }, {
        "serviceTypeId": "07d1020a28d540928745f9d3dbad494c",
        "serviceTypeName": "私人上门健身教练",
        "children": [{
            "serviceTypeId": "13316be43687474b9e9851594ba7f7c8",
            "serviceTypeName": "月卡",
            "ischecked": false
        }, {
            "serviceTypeId": "2c42826219b6433c9a3dd77b85bc3bf3",
            "serviceTypeName": "日卡",
            "ischecked": false
        }, {
            "serviceTypeId": "91537249d5794ed2bf844429a0a2d36c",
            "serviceTypeName": "年卡",
            "ischecked": false
        }, {
            "serviceTypeId": "661cf7fec7594d9b9d36a6416a3bc90d",
            "serviceTypeName": "会员",
            "ischecked": false
        }, {
            "serviceTypeId": "181c39c1b5f849f88f46aacc16e6735b",
            "serviceTypeName": "超级vip",
            "ischecked": false
        }],
        "ischecked": false
    }, {
        "serviceTypeId": "5025a90eefa1455dbd245eefc5c272b1",
        "serviceTypeName": "房屋装修",
        "children": [{
            "serviceTypeId": "3218f1510f064f4a92be5ac20ca4a43f",
            "serviceTypeName": "新房装修",
            "ischecked": false
        }, {
            "serviceTypeId": "337e978a91b64ffba2e45d0cd1c6163e",
            "serviceTypeName": "旧房装修",
            "ischecked": false
        }],
        "ischecked": false
    }, {
        "serviceTypeId": "97d50d66f5b14047ab389af1330a9827",
        "serviceTypeName": "幼教",
        "children": [{
            "serviceTypeId": "8d83405248284f1c9955c84c6d12acd8",
            "serviceTypeName": "托管",
            "ischecked": false
        }],
        "ischecked": false
    }, {
        "serviceTypeId": "cd1897c41f0b4886bf93e1cd1d68370c",
        "serviceTypeName": "房屋开锁",
        "children": [{
            "serviceTypeId": "7e770d826b3845e5905889e0588cad62",
            "serviceTypeName": "一般家庭防盗锁",
            "ischecked": false
        }, {
            "serviceTypeId": "311a1fc521f2415f99c329c11164dae3",
            "serviceTypeName": "密码锁",
            "ischecked": false
        }, {
            "serviceTypeId": "33f07b0683384c99a21ee6f3daeb39e1",
            "serviceTypeName": "声控锁",
            "ischecked": false
        }],
        "ischecked": false
    }, {
        "serviceTypeId": "cc3e5396a19449b7a5fafb4a35d09381",
        "serviceTypeName": "烧饭阿姨a",
        "children": [{
            "serviceTypeId": "ae4bc449376949dcb9a7c97f2d585082",
            "serviceTypeName": "一人",
            "ischecked": false
        }],
        "ischecked": false
    }, {
        "serviceTypeId": "430fd8a72a3e4b50a217b66be0966760",
        "serviceTypeName": "服务类型A04",
        "children": [{
            "serviceTypeId": "1e3d7aa8ebb54b8ab6d142f7d2d6720f",
            "serviceTypeName": "服务子类A0402",
            "ischecked": false
        }, {
            "serviceTypeId": "74dc14e660c54987a40721ca14bed067",
            "serviceTypeName": "服务类型A0401",
            "ischecked": false
        }],
        "ischecked": false
    }, {
        "serviceTypeId": "a7be787a4b174caebba55d302ac09382",
        "serviceTypeName": "家政新服务",
        "children": [{
            "serviceTypeId": "20979a47f66c41fbb9d24eac6f2f47ae",
            "serviceTypeName": "家政子服务1",
            "ischecked": false
        }, {
            "serviceTypeId": "813ed21e78a54dd2a48ca3d20918f681",
            "serviceTypeName": "家政子服务2",
            "ischecked": false
        }, {
            "serviceTypeId": "92a078853b144d89bfcdf3c63170a3c9",
            "serviceTypeName": "家政子服务3",
            "ischecked": false
        }],
        "ischecked": false
    }]
}